<?xml version="1.0" encoding="UTF-8"?>
<codehawk-java-analyzer>
  <header info="interface" time="2020-05-28 12:22:20"/>
  <interface name="RejectedExecutionHandler" package="java.util.concurrent">
    <superinterfaces/>
    <!-- =============================== FIELDS ===============================  -->
    <fields/>
    <!-- ============================== METHODS ==============================  -->
    <methods>
      <!-- ~~~~~~~~~~~~~~~~~~~~~~~~~~~~~~~~~~~~~~~~~~~~~~~~~~~ rejectedExecution -->
      <method abstract="yes" access="public" name="rejectedExecution" valid="no">
        <signature>
          <arg nr="1">
            <object>java.lang.Runnable</object>
          </arg>
          <arg nr="2">
            <object>java.util.concurrent.ThreadPoolExecutor</object>
          </arg>
        </signature>
        <exceptions/>
        <summary>
          <taint/>
        </summary>
      </method>
    </methods>
  </interface>
  <copyright-notice>Copyright 2012-2020, Kestrel Technology LLC, Palo Alto, CA 94304</copyright-notice>
</codehawk-java-analyzer>
