<?xml version="1.0" encoding="UTF-8"?>
<codehawk-java-analyzer>
  <header info="class" time="2020-03-12 14:34:48"/>
  <class name="BigInteger" immutable="yes" package="java.math">
    <superclass>java.lang.Number</superclass>
    <interfaces>
      <implements>java.lang.Comparable</implements>
      <implements>java.io.Serializable</implements>
    </interfaces>
    <class-properties>
      <cprop method="bitLength" name="size">
        <signature>
          <return>
            <int/>
          </return>
        </signature>
      </cprop>
    </class-properties>
    <!-- =============================== FIELDS ===============================  -->
    <fields>
      <!-- ~~~~~~~~~~~~~~~~~~~~~~~~~~~~~~~~~~~~~~~~~~~~~~~~~~~~~~~~~~ field:ZERO -->
      <field access="public" final="yes" name="ZERO" not-null="yes" static="yes">
        <signature>
          <object>java.math.BigInteger</object>
        </signature>
      </field>
      <!-- ~~~~~~~~~~~~~~~~~~~~~~~~~~~~~~~~~~~~~~~~~~~~~~~~~~~~~~~~~~~ field:ONE -->
      <field access="public" final="yes" name="ONE" not-null="yes" static="yes">
        <signature>
          <object>java.math.BigInteger</object>
        </signature>
      </field>
      <!-- ~~~~~~~~~~~~~~~~~~~~~~~~~~~~~~~~~~~~~~~~~~~~~~~~~~~~~~~~~~~ field:TEN -->
      <field access="public" final="yes" name="TEN" not-null="yes" static="yes">
        <signature>
          <object>java.math.BigInteger</object>
        </signature>
      </field>
    </fields>
    <!-- ============================ CONSTRUCTORS ============================  -->
    <constructors>
      <!-- ~~~~~~~~~~~~~~~~~~~~~~~~~~~~~~~~~~~~~~~~~~~~~~~~~~~~~~~~~~~~ (byte[]) -->
      <constructor access="public">
        <signature>
          <arg nr="1">
            <array>
              <byte/>
            </array>
          </arg>
        </signature>
        <exceptions>
          <throws>java.lang.NumberFormatException</throws>
        </exceptions>
        <summary>
          <taint>
            <transfer>
              <arg nr="1"/>
              <this/>
            </transfer>
          </taint>
        </summary>
      </constructor>
      <!-- ~~~~~~~~~~~~~~~~~~~~~~~~~~~~~~~~~~~~~~~~~~~~~~~~~~~~~~~~ (int,byte[]) -->
      <constructor access="public">
        <signature>
          <arg nr="1">
            <int/>
          </arg>
          <arg nr="2">
            <array>
              <byte/>
            </array>
          </arg>
        </signature>
        <exceptions>
          <throws>java.lang.NumberFormatException</throws>
        </exceptions>
        <summary>
          <taint>
            <transfer>
              <arg nr="1"/>
              <this/>
            </transfer>
            <transfer>
              <arg nr="2"/>
              <this/>
            </transfer>
          </taint>
        </summary>
      </constructor>
      <!-- ~~~~~~~~~~~~~~~~~~~~~~~~~~~~~~~~~~~~~~~~~~~~~~ (java.lang.String,int) -->
      <constructor access="public">
        <signature>
          <arg nr="1">
            <object>java.lang.String</object>
          </arg>
          <arg nr="2">
            <int/>
          </arg>
        </signature>
        <exceptions>
          <throws>java.lang.NumberFormatException</throws>
        </exceptions>
        <summary>
          <taint>
            <transfer>
              <arg nr="1"/>
              <this/>
            </transfer>
            <transfer>
              <arg nr="2"/>
              <this/>
            </transfer>
          </taint>
        </summary>
      </constructor>
      <!-- ~~~~~~~~~~~~~~~~~~~~~~~~~~~~~~~~~~~~~~~~~~~~~~~~~~ (java.lang.String) -->
      <constructor access="public">
        <signature>
          <arg nr="1">
            <object>java.lang.String</object>
          </arg>
        </signature>
        <exceptions>
          <throws>java.lang.NumberFormatException</throws>
        </exceptions>
        <summary>
          <taint>
            <transfer>
              <arg nr="1"/>
              <this/>
            </transfer>
          </taint>
        </summary>
      </constructor>
      <!-- ~~~~~~~~~~~~~~~~~~~~~~~~~~~~~~~~~~~~~~~~~~~~~~ (int,java.util.Random) -->
      <constructor access="public">
        <signature>
          <arg nr="1">
            <int/>
          </arg>
          <arg nr="2">
            <object>java.util.Random</object>
          </arg>
        </signature>
        <exceptions>
          <throws>java.lang.IllegalArgumentException</throws>
        </exceptions>
        <summary>
          <taint>
            <transfer>
              <arg nr="1"/>
              <this/>
            </transfer>
            <transfer>
              <arg nr="2"/>
              <this/>
            </transfer>
          </taint>
        </summary>
      </constructor>
      <!-- ~~~~~~~~~~~~~~~~~~~~~~~~~~~~~~~~~~~~~~~~~~ (int,int,java.util.Random) -->
      <constructor access="public">
        <signature>
          <arg nr="1">
            <int/>
          </arg>
          <arg nr="2">
            <int/>
          </arg>
          <arg nr="3">
            <object>java.util.Random</object>
          </arg>
        </signature>
        <exceptions>
          <throws>java.lang.ArithmeticException</throws>
        </exceptions>
        <summary>
          <taint>
            <transfer>
              <arg nr="1"/>
              <this/>
            </transfer>
            <transfer>
              <arg nr="2"/>
              <this/>
            </transfer>
            <transfer>
              <arg nr="3"/>
              <this/>
            </transfer>
          </taint>
        </summary>
      </constructor>
    </constructors>
    <!-- ============================== METHODS ==============================  -->
    <methods>
      <!-- ~~~~~~~~~~~~~~~~~~~~~~~~~~~~~~~~~~~~~~~~~~~~~~~~~~~~~~~~~~~~~~~~~ abs -->
      <method access="public" name="abs">
        <signature>
          <return>
            <object>java.math.BigInteger</object>
          </return>
        </signature>
        <exceptions/>
        <summary>
          <taint>
            <transfer>
              <this/>
              <return/>
            </transfer>
          </taint>
          <postconditions>
            <post>
              <math>
                <not-null/>
              </math>
            </post>
          </postconditions>
        </summary>
      </method>
      <!-- ~~~~~~~~~~~~~~~~~~~~~~~~~~~~~~~~~~~~~~~~~~~~~~~~~~~~~~~~~~~~~~~~~ add -->
      <method access="public" name="add">
        <signature>
          <arg nr="1">
            <object>java.math.BigInteger</object>
          </arg>
          <return>
            <object>java.math.BigInteger</object>
          </return>
        </signature>
        <exceptions/>
        <summary>
          <taint>
            <transfer>
              <arg nr="1"/>
              <return/>
            </transfer>
            <transfer>
              <this/>
              <return/>
            </transfer>
          </taint>
          <postconditions>
            <post>
              <math>
                <not-null/>
              </math>
            </post>
          </postconditions>
        </summary>
      </method>
      <!-- ~~~~~~~~~~~~~~~~~~~~~~~~~~~~~~~~~~~~~~~~~~~~~~~~~~~~~~~~~~~~~~~~~ and -->
      <method access="public" name="and">
        <signature>
          <arg nr="1">
            <object>java.math.BigInteger</object>
          </arg>
          <return>
            <object>java.math.BigInteger</object>
          </return>
        </signature>
        <exceptions/>
        <summary>
          <taint>
            <transfer>
              <arg nr="1"/>
              <return/>
            </transfer>
            <transfer>
              <this/>
              <return/>
            </transfer>
          </taint>
          <postconditions>
            <post>
              <math>
                <not-null/>
              </math>
            </post>
          </postconditions>
        </summary>
      </method>
      <!-- ~~~~~~~~~~~~~~~~~~~~~~~~~~~~~~~~~~~~~~~~~~~~~~~~~~~~~~~~~~~~~~ andNot -->
      <method access="public" name="andNot">
        <signature>
          <arg nr="1">
            <object>java.math.BigInteger</object>
          </arg>
          <return>
            <object>java.math.BigInteger</object>
          </return>
        </signature>
        <exceptions/>
        <summary>
          <taint>
	    <transfer>
	      <this/>
	      <return/>
	    </transfer>
	    <transfer>
	      <arg nr="1"/>
	      <return/>
	    </transfer>
	  </taint>
        </summary>
      </method>
      <!-- ~~~~~~~~~~~~~~~~~~~~~~~~~~~~~~~~~~~~~~~~~~~~~~~~~~~~~~~~~~~~ bitCount -->
      <method access="public" name="bitCount">
        <signature>
          <return>
            <int/>
          </return>
        </signature>
        <exceptions/>
        <summary>
          <taint>
            <transfer>
              <this/>
              <return/>
            </transfer>
          </taint>
          <postconditions>
            <post>
              <math>
                <apply>
                  <geq/>
                  <return/>
                  <cn>0</cn>
                </apply>
              </math>
            </post>
          </postconditions>
        </summary>
      </method>
      <!-- ~~~~~~~~~~~~~~~~~~~~~~~~~~~~~~~~~~~~~~~~~~~~~~~~~~~~~~~~~~~ bitLength -->
      <method access="public" name="bitLength">
        <signature>
          <return>
            <int/>
          </return>
        </signature>
        <exceptions/>
        <summary>
          <taint>
            <transfer>
              <this/>
              <return/>
            </transfer>
          </taint>
          <postconditions>
            <post>
              <math>
                <apply>
                  <geq/>
                  <return/>
                  <cn>0</cn>
                </apply>
              </math>
            </post>
          </postconditions>
        </summary>
      </method>
      <!-- ~~~~~~~~~~~~~~~~~~~~~~~~~~~~~~~~~~~~~~~~~~~~~~~~~~~~~~ byteValueExact -->
      <method access="public" name="byteValueExact">
        <signature>
          <return>
            <byte/>
          </return>
        </signature>
        <exceptions/>
        <summary>
          <taint>
	    <transfer>
	      <this/>
	      <return/>
	    </transfer>
	  </taint>
        </summary>
      </method>
      <!-- ~~~~~~~~~~~~~~~~~~~~~~~~~~~~~~~~~~~~~~~~~~~~~~~~~~~~~~~~~~~~ clearBit -->
      <method access="public" name="clearBit">
        <signature>
          <arg nr="1">
            <int/>
          </arg>
          <return>
            <object>java.math.BigInteger</object>
          </return>
        </signature>
        <exceptions>
          <c-throws>
            <safety-condition>
              <math>
                <apply>
                  <geq/>
                  <arg nr="1"/>
                  <cn>0</cn>
                </apply>
              </math>
            </safety-condition>
            <exn>java.lang.ArithmeticException</exn>
          </c-throws>
        </exceptions>
        <summary>
          <taint>
            <transfer>
              <arg nr="1"/>
              <return/>
            </transfer>
            <transfer>
              <this/>
              <return/>
            </transfer>
          </taint>
        </summary>
      </method>
      <!-- ~~~~~~~~~~~~~~~~~~~~~~~~~~~~~~~~~~~~~~~~~~~~~~~~~~~~~~~~~~~ compareTo -->
      <method access="public" name="compareTo">
        <signature>
          <arg nr="1">
            <object>java.math.BigInteger</object>
          </arg>
          <return>
            <int/>
          </return>
        </signature>
        <exceptions>
          <throws>java.lang.NullPointerException</throws>
        </exceptions>
        <summary>
          <taint>
            <transfer>
              <this/>
              <return/>
            </transfer>
            <transfer>
              <arg nr="1"/>
              <return/>
            </transfer>
          </taint>
          <postconditions>
            <post>
              <math>
                <apply>
                  <geq/>
                  <return/>
                  <cn>-1</cn>
                </apply>
              </math>
            </post>
            <post>
              <math>
                <apply>
                  <leq/>
                  <return/>
                  <cn>1</cn>
                </apply>
              </math>
            </post>
          </postconditions>
        </summary>
      </method>
      <!-- ~~~~~~~~~~~~~~~~~~~~~~~~~~~~~~~~~~~~~~~~~~~~~~~~~~~~~~~~~~~ compareTo -->
      <method access="public" bridge="yes" name="compareTo">
        <signature>
          <arg nr="1">
            <object>java.lang.Object</object>
          </arg>
          <return>
            <int/>
          </return>
        </signature>
        <exceptions>
          <throws>java.lang.NullPointerException</throws>
        </exceptions>
        <summary>
          <taint>
            <transfer>
              <arg nr="1"/>
              <return/>
            </transfer>
            <transfer>
              <this/>
              <return/>
            </transfer>
          </taint>
          <postconditions>
            <post>
              <math>
                <apply>
                  <geq/>
                  <return/>
                  <cn>-1</cn>
                </apply>
              </math>
            </post>
            <post>
              <math>
                <apply>
                  <leq/>
                  <return/>
                  <cn>1</cn>
                </apply>
              </math>
            </post>
          </postconditions>
        </summary>
      </method>
      <!-- ~~~~~~~~~~~~~~~~~~~~~~~~~~~~~~~~~~~~~~~~~~~~~~~~~~~~~~~~~~~~~~ divide -->
      <method access="public" name="divide">
        <signature>
          <arg nr="1">
            <object>java.math.BigInteger</object>
          </arg>
          <return>
            <object>java.math.BigInteger</object>
          </return>
        </signature>
        <exceptions>
          <throws>java.lang.ArithmeticException</throws>
        </exceptions>
        <summary>
          <taint>
            <transfer>
              <arg nr="1"/>
              <return/>
            </transfer>
            <transfer>
              <this/>
              <return/>
            </transfer>
          </taint>
          <postconditions>
            <post>
              <math>
                <not-null/>
              </math>
            </post>
          </postconditions>
        </summary>
      </method>
      <!-- ~~~~~~~~~~~~~~~~~~~~~~~~~~~~~~~~~~~~~~~~~~~~~~~~~~ divideAndRemainder -->
      <method access="public" name="divideAndRemainder">
        <signature>
          <arg nr="1">
            <object>java.math.BigInteger</object>
          </arg>
          <return>
            <array>
              <object>java.math.BigInteger</object>
            </array>
          </return>
        </signature>
        <exceptions>
          <throws>java.lang.ArithmeticException</throws>
        </exceptions>
        <summary>
          <taint>
            <transfer>
              <arg nr="1"/>
              <return/>
            </transfer>
            <transfer>
              <this/>
              <return/>
            </transfer>
          </taint>
          <postconditions>
            <post>
              <math>
                <not-null/>
              </math>
            </post>
          </postconditions>
        </summary>
      </method>
      <!-- ~~~~~~~~~~~~~~~~~~~~~~~~~~~~~~~~~~~~~~~~~~~~~~~~~~~~~~~~~ doubleValue -->
      <method access="public" name="doubleValue">
        <signature>
          <return>
            <double/>
          </return>
        </signature>
        <exceptions/>
        <summary>
          <taint>
            <transfer>
              <this/>
              <return/>
            </transfer>
          </taint>
        </summary>
      </method>
      <!-- ~~~~~~~~~~~~~~~~~~~~~~~~~~~~~~~~~~~~~~~~~~~~~~~~~~~~~~~~~~~~~~ equals -->
      <method access="public" name="equals">
        <signature>
          <arg nr="1">
            <object>java.lang.Object</object>
          </arg>
          <return>
            <boolean/>
          </return>
        </signature>
        <exceptions/>
        <summary>
          <taint>
            <transfer>
              <arg nr="1"/>
              <return/>
            </transfer>
            <transfer>
              <this/>
              <return/>
            </transfer>
          </taint>
        </summary>
      </method>
      <!-- ~~~~~~~~~~~~~~~~~~~~~~~~~~~~~~~~~~~~~~~~~~~~~~~~~~~~~~~~~~~~~ flipBit -->
      <method access="public" name="flipBit">
        <signature>
          <arg nr="1">
            <int/>
          </arg>
          <return>
            <object>java.math.BigInteger</object>
          </return>
        </signature>
        <exceptions/>
        <summary>
          <taint>
	    <transfer>
	      <this/>
	      <return/>
	    </transfer>
	    <transfer>
	      <arg nr="1"/>
	      <return/>
	    </transfer>
	  </taint>
        </summary>
      </method>
      <!-- ~~~~~~~~~~~~~~~~~~~~~~~~~~~~~~~~~~~~~~~~~~~~~~~~~~~~~~~~~~ floatValue -->
      <method access="public" name="floatValue">
        <signature>
          <return>
            <float/>
          </return>
        </signature>
        <exceptions/>
        <summary>
          <taint>
            <transfer>
              <this/>
              <return/>
            </transfer>
          </taint>
        </summary>
      </method>
      <!-- ~~~~~~~~~~~~~~~~~~~~~~~~~~~~~~~~~~~~~~~~~~~~~~~~~~~~~~~~~~~~~~~~~ gcd -->
      <method access="public" name="gcd">
        <signature>
          <arg nr="1">
            <object>java.math.BigInteger</object>
          </arg>
          <return>
            <object>java.math.BigInteger</object>
          </return>
        </signature>
        <exceptions/>
        <summary>
          <taint>
            <transfer>
              <arg nr="1"/>
              <return/>
            </transfer>
            <transfer>
              <this/>
              <return/>
            </transfer>
          </taint>
          <postconditions>
            <post>
              <math>
                <not-null/>
              </math>
            </post>
          </postconditions>
        </summary>
      </method>
      <!-- ~~~~~~~~~~~~~~~~~~~~~~~~~~~~~~~~~~~~~~~~~~~~~~~~~~~~~ getLowestSetBit -->
      <method access="public" name="getLowestSetBit">
        <signature>
          <return>
            <int/>
          </return>
        </signature>
        <exceptions/>
        <summary>
          <taint>
            <transfer>
              <this/>
              <return/>
            </transfer>
          </taint>
          <postconditions>
            <post>
              <math>
                <apply>
                  <geq/>
                  <return/>
                  <cn>0</cn>
                </apply>
              </math>
            </post>
          </postconditions>
        </summary>
      </method>
      <!-- ~~~~~~~~~~~~~~~~~~~~~~~~~~~~~~~~~~~~~~~~~~~~~~~~~~~~~~~~~~~~ hashCode -->
      <method access="public" name="hashCode">
        <signature>
          <return>
            <int/>
          </return>
        </signature>
        <exceptions/>
        <summary>
          <taint>
            <transfer>
              <this/>
              <return/>
            </transfer>
          </taint>
        </summary>
      </method>
      <!-- ~~~~~~~~~~~~~~~~~~~~~~~~~~~~~~~~~~~~~~~~~~~~~~~~~~~~~~~~~~~~ intValue -->
      <method access="public" name="intValue">
        <signature>
          <return>
            <int/>
          </return>
        </signature>
        <exceptions/>
        <summary>
          <taint>
            <transfer>
              <this/>
              <return/>
            </transfer>
          </taint>
        </summary>
      </method>
      <!-- ~~~~~~~~~~~~~~~~~~~~~~~~~~~~~~~~~~~~~~~~~~~~~~~~~~~~~~~ intValueExact -->
      <method access="public" name="intValueExact">
        <signature>
          <return>
            <int/>
          </return>
        </signature>
        <exceptions/>
        <summary>
          <taint>
	    <transfer>
	      <this/>
	      <return/>
	    </transfer>
	  </taint>
        </summary>
      </method>
      <!-- ~~~~~~~~~~~~~~~~~~~~~~~~~~~~~~~~~~~~~~~~~~~~~~~~~~~~~ isProbablePrime -->
      <method access="public" name="isProbablePrime">
        <signature>
          <arg nr="1">
            <int/>
          </arg>
          <return>
            <boolean/>
          </return>
        </signature>
        <exceptions/>
        <summary>
          <taint>
	    <transfer>
	      <this/>
	      <return/>
	    </transfer>
	    <transfer>
	      <arg nr="1"/>
	      <return/>
	    </transfer>
	  </taint>
        </summary>
      </method>
      <!-- ~~~~~~~~~~~~~~~~~~~~~~~~~~~~~~~~~~~~~~~~~~~~~~~~~~~~~~~~~~~ longValue -->
      <method access="public" name="longValue">
        <signature>
          <return>
            <long/>
          </return>
        </signature>
        <exceptions/>
        <summary>
          <taint>
            <transfer>
              <this/>
              <return/>
            </transfer>
          </taint>
        </summary>
      </method>
      <!-- ~~~~~~~~~~~~~~~~~~~~~~~~~~~~~~~~~~~~~~~~~~~~~~~~~~~~~~ longValueExact -->
      <method access="public" name="longValueExact">
        <signature>
          <return>
            <long/>
          </return>
        </signature>
        <exceptions/>
        <summary>
          <taint>
	    <transfer>
	      <this/>
	      <return/>
	    </transfer>
	  </taint>
        </summary>
      </method>
      <!-- ~~~~~~~~~~~~~~~~~~~~~~~~~~~~~~~~~~~~~~~~~~~~~~~~~~~~~~~~~~~~~~~~~ max -->
      <method access="public" name="max">
        <signature>
          <arg nr="1">
            <object>java.math.BigInteger</object>
          </arg>
          <return>
            <object>java.math.BigInteger</object>
          </return>
        </signature>
        <exceptions/>
        <summary>
          <taint>
	    <transfer>
	      <arg nr="1"/>
	      <return/>
	    </transfer>
	    <transfer>
	      <this/>
	      <return/>
	    </transfer>
	  </taint>
        </summary>
      </method>
      <!-- ~~~~~~~~~~~~~~~~~~~~~~~~~~~~~~~~~~~~~~~~~~~~~~~~~~~~~~~~~~~~~~~~~ min -->
      <method access="public" name="min">
        <signature>
          <arg nr="1">
            <object>java.math.BigInteger</object>
          </arg>
          <return>
            <object>java.math.BigInteger</object>
          </return>
        </signature>
        <exceptions/>
        <summary>
          <taint>
	    <transfer>
	      <arg nr="1"/>
	      <return/>
	    </transfer>
	    <transfer>
	      <this/>
	      <return/>
	    </transfer>
	  </taint>
        </summary>
      </method>
      <!-- ~~~~~~~~~~~~~~~~~~~~~~~~~~~~~~~~~~~~~~~~~~~~~~~~~~~~~~~~~~~~~~~~~ mod -->
      <method access="public" name="mod">
        <signature>
          <arg nr="1">
            <object>java.math.BigInteger</object>
          </arg>
          <return>
            <object>java.math.BigInteger</object>
          </return>
        </signature>
        <exceptions>
          <c-throws>
            <safety-condition>
              <math>
                <apply>
                  <geq/>
                  <arg nr="1"/>
                  <cn>1</cn>
                </apply>
              </math>
            </safety-condition>
            <exn>java.lang.ArithmeticException</exn>
          </c-throws>
        </exceptions>
        <summary>
          <taint>
            <transfer>
              <arg nr="1"/>
              <return/>
            </transfer>
            <transfer>
              <this/>
              <return/>
            </transfer>
          </taint>
          <postconditions>
            <post>
              <math>
                <not-null/>
              </math>
            </post>
          </postconditions>
        </summary>
      </method>
      <!-- ~~~~~~~~~~~~~~~~~~~~~~~~~~~~~~~~~~~~~~~~~~~~~~~~~~~~~~~~~~ modInverse -->
      <method access="public" name="modInverse">
        <signature>
          <arg nr="1">
            <object>java.math.BigInteger</object>
          </arg>
          <return>
            <object>java.math.BigInteger</object>
          </return>
        </signature>
        <exceptions>
          <throws>java.lang.ArithmeticException</throws>
        </exceptions>
        <summary>
          <taint>
            <transfer>
              <arg nr="1"/>
              <return/>
            </transfer>
            <transfer>
              <this/>
              <return/>
            </transfer>
          </taint>
          <postconditions>
            <post>
              <math>
                <not-null/>
              </math>
            </post>
          </postconditions>
        </summary>
      </method>
      <!-- ~~~~~~~~~~~~~~~~~~~~~~~~~~~~~~~~~~~~~~~~~~~~~~~~~~~~~~~~~~~~~~ modPow -->
      <method access="public" name="modPow">
        <signature>
          <arg nr="1">
            <object>java.math.BigInteger</object>
          </arg>
          <arg nr="2">
            <object>java.math.BigInteger</object>
          </arg>
          <return>
            <object>java.math.BigInteger</object>
          </return>
        </signature>
        <exceptions>
          <throws>java.lang.ArithmeticException</throws>
        </exceptions>
        <summary>
          <taint>
            <transfer>
              <arg nr="1"/>
              <return/>
            </transfer>
            <transfer>
              <arg nr="2"/>
              <return/>
            </transfer>
            <transfer>
              <this/>
              <return/>
            </transfer>
          </taint>
          <postconditions>
            <post>
              <math>
                <not-null/>
              </math>
            </post>
          </postconditions>
        </summary>
      </method>
      <!-- ~~~~~~~~~~~~~~~~~~~~~~~~~~~~~~~~~~~~~~~~~~~~~~~~~~~~~~~~~~~~ multiply -->
      <method access="public" name="multiply">
        <signature>
          <arg nr="1">
            <object>java.math.BigInteger</object>
          </arg>
          <return>
            <object>java.math.BigInteger</object>
          </return>
        </signature>
        <exceptions/>
        <summary>
          <taint>
            <transfer>
              <arg nr="1"/>
              <return/>
            </transfer>
            <transfer>
              <this/>
              <return/>
            </transfer>
          </taint>
          <postconditions>
            <post>
              <math>
                <not-null/>
              </math>
            </post>
          </postconditions>
        </summary>
      </method>
      <!-- ~~~~~~~~~~~~~~~~~~~~~~~~~~~~~~~~~~~~~~~~~~~~~~~~~~~~~~~~~~~~~~ negate -->
      <method access="public" name="negate">
        <signature>
          <return>
            <object>java.math.BigInteger</object>
          </return>
        </signature>
        <exceptions/>
        <summary>
          <taint>
            <transfer>
              <this/>
              <return/>
            </transfer>
          </taint>
          <postconditions>
            <post>
              <math>
                <not-null/>
              </math>
            </post>
          </postconditions>
        </summary>
      </method>
      <!-- ~~~~~~~~~~~~~~~~~~~~~~~~~~~~~~~~~~~~~~~~~~~~~~~~~~~ nextProbablePrime -->
      <method access="public" name="nextProbablePrime">
        <signature>
          <return>
            <object>java.math.BigInteger</object>
          </return>
        </signature>
        <exceptions/>
        <summary>
          <taint>
	    <transfer>
	      <this/>
	      <return/>
	    </transfer>
	  </taint>
        </summary>
      </method>
      <!-- ~~~~~~~~~~~~~~~~~~~~~~~~~~~~~~~~~~~~~~~~~~~~~~~~~~~~~~~~~~~~~~~~~ not -->
      <method access="public" name="not">
        <signature>
          <return>
            <object>java.math.BigInteger</object>
          </return>
        </signature>
        <exceptions/>
        <summary>
          <taint>
            <transfer>
              <this/>
              <return/>
            </transfer>
          </taint>
          <postconditions>
            <post>
              <math>
                <not-null/>
              </math>
            </post>
          </postconditions>
        </summary>
      </method>
      <!-- ~~~~~~~~~~~~~~~~~~~~~~~~~~~~~~~~~~~~~~~~~~~~~~~~~~~~~~~~~~~~~~~~~~ or -->
      <method access="public" name="or">
        <signature>
          <arg nr="1">
            <object>java.math.BigInteger</object>
          </arg>
          <return>
            <object>java.math.BigInteger</object>
          </return>
        </signature>
        <exceptions/>
        <summary>
          <taint>
            <transfer>
              <arg nr="1"/>
              <return/>
            </transfer>
            <transfer>
              <this/>
              <return/>
            </transfer>
          </taint>
        </summary>
      </method>
      <!-- ~~~~~~~~~~~~~~~~~~~~~~~~~~~~~~~~~~~~~~~~~~~~~~~~~~~~~~~~~~~~~~~~~ pow -->
      <method access="public" name="pow">
        <signature>
          <arg nr="1">
            <int/>
          </arg>
          <return>
            <object>java.math.BigInteger</object>
          </return>
        </signature>
        <exceptions>
          <c-throws>
            <safety-condition>
              <math>
                <apply>
                  <geq/>
                  <arg nr="1"/>
                  <cn>0</cn>
                </apply>
              </math>
            </safety-condition>
            <exn>java.lang.ArithmeticException</exn>
          </c-throws>
        </exceptions>
        <summary>
          <taint>
            <transfer>
              <arg nr="1"/>
              <return/>
            </transfer>
            <transfer>
              <this/>
              <return/>
            </transfer>
          </taint>
        </summary>
      </method>
      <!-- ~~~~~~~~~~~~~~~~~~~~~~~~~~~~~~~~~~~~~~~~~~~~~~~~~~~~~~~ probablePrime -->
      <method access="public" name="probablePrime" static="yes">
        <signature>
          <arg nr="1">
            <int/>
          </arg>
          <arg nr="2">
            <object>java.util.Random</object>
          </arg>
          <return>
            <object>java.math.BigInteger</object>
          </return>
        </signature>
        <exceptions>
          <throws>java.lang.ArithmeticException</throws>
        </exceptions>
        <summary>
          <taint>
            <transfer>
              <arg nr="1"/>
              <return/>
            </transfer>
            <transfer>
              <arg nr="2"/>
              <return/>
            </transfer>
          </taint>
          <postconditions>
            <post>
              <math>
                <not-null/>
              </math>
            </post>
          </postconditions>
        </summary>
      </method>
      <!-- ~~~~~~~~~~~~~~~~~~~~~~~~~~~~~~~~~~~~~~~~~~~~~~~~~~~~~~~~~~~ remainder -->
      <method access="public" name="remainder">
        <signature>
          <arg nr="1">
            <object>java.math.BigInteger</object>
          </arg>
          <return>
            <object>java.math.BigInteger</object>
          </return>
        </signature>
        <exceptions>
          <throws>java.lang.ArithmeticException</throws>
        </exceptions>
        <summary>
          <taint>
            <transfer>
              <arg nr="1"/>
              <return/>
            </transfer>
            <transfer>
              <this/>
              <return/>
            </transfer>
          </taint>
        </summary>
      </method>
      <!-- ~~~~~~~~~~~~~~~~~~~~~~~~~~~~~~~~~~~~~~~~~~~~~~~~~~~~~~~~~~~~~~ setBit -->
      <method access="public" name="setBit">
        <signature>
          <arg nr="1">
            <int/>
          </arg>
          <return>
            <object>java.math.BigInteger</object>
          </return>
        </signature>
        <exceptions/>
        <summary>
          <taint>
	    <transfer>
	      <this/>
	      <return/>
	    </transfer>
	    <transfer>
	      <arg nr="1"/>
	      <return/>
	    </transfer>
	  </taint>
        </summary>
      </method>
      <!-- ~~~~~~~~~~~~~~~~~~~~~~~~~~~~~~~~~~~~~~~~~~~~~~~~~~~~~~~~~~~ shiftLeft -->
      <method access="public" name="shiftLeft">
        <signature>
          <arg nr="1">
            <int/>
          </arg>
          <return>
            <object>java.math.BigInteger</object>
          </return>
        </signature>
        <exceptions>
          <throws>java.lang.ArithmeticException</throws>
        </exceptions>
        <summary>
          <taint>
            <transfer>
              <arg nr="1"/>
              <return/>
            </transfer>
            <transfer>
              <this/>
              <return/>
            </transfer>
          </taint>
          <postconditions>
            <post>
              <math>
                <not-null/>
              </math>
            </post>
          </postconditions>
        </summary>
      </method>
      <!-- ~~~~~~~~~~~~~~~~~~~~~~~~~~~~~~~~~~~~~~~~~~~~~~~~~~~~~~~~~~ shiftRight -->
      <method access="public" name="shiftRight">
        <signature>
          <arg nr="1">
            <int/>
          </arg>
          <return>
            <object>java.math.BigInteger</object>
          </return>
        </signature>
        <exceptions>
          <throws>java.lang.ArithmeticException</throws>
        </exceptions>
        <summary>
          <taint>
            <transfer>
              <arg nr="1"/>
              <return/>
            </transfer>
            <transfer>
              <this/>
              <return/>
            </transfer>
          </taint>
          <postconditions>
            <post>
              <math>
                <not-null/>
              </math>
            </post>
          </postconditions>
        </summary>
      </method>
      <!-- ~~~~~~~~~~~~~~~~~~~~~~~~~~~~~~~~~~~~~~~~~~~~~~~~~~~~~ shortValueExact -->
      <method access="public" name="shortValueExact">
        <signature>
          <return>
            <short/>
          </return>
        </signature>
        <exceptions/>
        <summary>
          <taint>
	    <transfer>
	      <this/>
	      <return/>
	    </transfer>
	  </taint>
        </summary>
      </method>
      <!-- ~~~~~~~~~~~~~~~~~~~~~~~~~~~~~~~~~~~~~~~~~~~~~~~~~~~~~~~~~~~~~~ signum -->
      <method access="public" name="signum">
        <signature>
          <return>
            <int/>
          </return>
        </signature>
        <exceptions/>
        <summary>
          <taint>
            <transfer>
              <this/>
              <return/>
            </transfer>
          </taint>
          <postconditions>
            <post>
              <math>
                <apply>
                  <geq/>
                  <return/>
                  <cn>-1</cn>
                </apply>
              </math>
            </post>
            <post>
              <math>
                <apply>
                  <leq/>
                  <return/>
                  <cn>1</cn>
                </apply>
              </math>
            </post>
          </postconditions>
        </summary>
      </method>
      <!-- ~~~~~~~~~~~~~~~~~~~~~~~~~~~~~~~~~~~~~~~~~~~~~~~~~~~~~~~~~~~~ subtract -->
      <method access="public" name="subtract">
        <signature>
          <arg nr="1">
            <object>java.math.BigInteger</object>
          </arg>
          <return>
            <object>java.math.BigInteger</object>
          </return>
        </signature>
        <exceptions/>
        <summary>
          <taint>
            <transfer>
              <arg nr="1"/>
              <return/>
            </transfer>
            <transfer>
              <this/>
              <return/>
            </transfer>
          </taint>
        </summary>
      </method>
      <!-- ~~~~~~~~~~~~~~~~~~~~~~~~~~~~~~~~~~~~~~~~~~~~~~~~~~~~~~~~~~~~~ testBit -->
      <method access="public" name="testBit">
        <signature>
          <arg nr="1">
            <int/>
          </arg>
          <return>
            <boolean/>
          </return>
        </signature>
        <exceptions>
          <c-throws>
            <safety-condition>
              <math>
                <apply>
                  <geq/>
                  <arg nr="1"/>
                  <cn>0</cn>
                </apply>
              </math>
            </safety-condition>
            <exn>java.lang.ArithmeticException</exn>
          </c-throws>
        </exceptions>
        <summary>
          <taint>
            <transfer>
              <arg nr="1"/>
              <return/>
            </transfer>
            <transfer>
              <this/>
              <return/>
            </transfer>
          </taint>
        </summary>
      </method>
      <!-- ~~~~~~~~~~~~~~~~~~~~~~~~~~~~~~~~~~~~~~~~~~~~~~~~~~~~~~~~~ toByteArray -->
      <method access="public" name="toByteArray">
        <signature>
          <return>
            <array>
              <byte/>
            </array>
          </return>
        </signature>
        <exceptions/>
        <summary>
          <taint>
            <transfer>
              <this/>
              <return/>
            </transfer>
          </taint>
          <postconditions>
            <post>
              <math>
                <not-null/>
              </math>
            </post>
          </postconditions>
        </summary>
      </method>
      <!-- ~~~~~~~~~~~~~~~~~~~~~~~~~~~~~~~~~~~~~~~~~~~~~~~~~~~~~~~~~~~~ toString -->
      <method access="public" name="toString">
        <signature>
          <arg nr="1">
            <int/>
          </arg>
          <return>
            <object>java.lang.String</object>
          </return>
        </signature>
        <exceptions/>
        <summary>
          <taint>
            <transfer>
              <arg nr="1"/>
              <return/>
            </transfer>
            <transfer>
              <this/>
              <return/>
            </transfer>
          </taint>
        </summary>
      </method>
      <!-- ~~~~~~~~~~~~~~~~~~~~~~~~~~~~~~~~~~~~~~~~~~~~~~~~~~~~~~~~~~~~ toString -->
      <method access="public" name="toString">
        <signature>
          <return>
            <object>java.lang.String</object>
          </return>
        </signature>
        <exceptions/>
        <summary>
          <taint>
            <transfer>
              <this/>
              <return/>
            </transfer>
          </taint>
        </summary>
      </method>
      <!-- ~~~~~~~~~~~~~~~~~~~~~~~~~~~~~~~~~~~~~~~~~~~~~~~~~~~~~~~~~~~~~ valueOf -->
      <method access="public" name="valueOf" static="yes">
        <signature>
          <arg nr="1">
            <long/>
          </arg>
          <return>
            <object>java.math.BigInteger</object>
          </return>
        </signature>
        <exceptions/>
        <summary>
          <taint>
            <transfer>
              <arg nr="1"/>
              <return/>
            </transfer>
          </taint>
          <postconditions>
            <post>
              <math>
                <not-null/>
              </math>
            </post>
          </postconditions>
        </summary>
      </method>
      <!-- ~~~~~~~~~~~~~~~~~~~~~~~~~~~~~~~~~~~~~~~~~~~~~~~~~~~~~~~~~~~~~~~~~ xor -->
      <method access="public" name="xor">
        <signature>
          <arg nr="1">
            <object>java.math.BigInteger</object>
          </arg>
          <return>
            <object>java.math.BigInteger</object>
          </return>
        </signature>
        <exceptions/>
        <summary>
          <taint>
            <transfer>
              <arg nr="1"/>
              <return/>
            </transfer>
            <transfer>
              <this/>
              <return/>
            </transfer>
          </taint>
        </summary>
      </method>
      <!-- ~~~~~~~~~~~~~~~~~~~~~~~~~~~~~~~~~~~~~~~~~~~~~~~ (inherited) byteValue -->
      <method from="java.lang.Number" inherited="yes" name="byteValue">
        <signature>
          <return>
            <byte/>
          </return>
        </signature>
      </method>
      <!-- ~~~~~~~~~~~~~~~~~~~~~~~~~~~~~~~~~~~~~~~~~~~~~~~~~~~ (inherited) clone -->
      <method from="java.lang.Object" inherited="yes" name="clone">
        <signature>
          <return>
            <object>java.lang.Object</object>
          </return>
        </signature>
      </method>
      <!-- ~~~~~~~~~~~~~~~~~~~~~~~~~~~~~~~~~~~~~~~~~~~~~~~~ (inherited) finalize -->
      <method from="java.lang.Object" inherited="yes" name="finalize">
        <signature/>
      </method>
      <!-- ~~~~~~~~~~~~~~~~~~~~~~~~~~~~~~~~~~~~~~~~~~~~~~~~ (inherited) getClass -->
      <method from="java.lang.Object" inherited="yes" name="getClass">
        <signature>
          <return>
            <object>java.lang.Class</object>
          </return>
        </signature>
      </method>
      <!-- ~~~~~~~~~~~~~~~~~~~~~~~~~~~~~~~~~~~~~~~~~~~~~~~~~~ (inherited) notify -->
      <method from="java.lang.Object" inherited="yes" name="notify">
        <signature/>
      </method>
      <!-- ~~~~~~~~~~~~~~~~~~~~~~~~~~~~~~~~~~~~~~~~~~~~~~~ (inherited) notifyAll -->
      <method from="java.lang.Object" inherited="yes" name="notifyAll">
        <signature/>
      </method>
      <!-- ~~~~~~~~~~~~~~~~~~~~~~~~~~~~~~~~~~~~~~~~~~~~~~ (inherited) shortValue -->
      <method from="java.lang.Number" inherited="yes" name="shortValue">
        <signature>
          <return>
            <short/>
          </return>
        </signature>
      </method>
      <!-- ~~~~~~~~~~~~~~~~~~~~~~~~~~~~~~~~~~~~~~~~~~~~~~~~~~~~ (inherited) wait -->
      <method from="java.lang.Object" inherited="yes" name="wait">
        <signature/>
      </method>
      <!-- ~~~~~~~~~~~~~~~~~~~~~~~~~~~~~~~~~~~~~~~~~~~~~~~~~~~~ (inherited) wait -->
      <method from="java.lang.Object" inherited="yes" name="wait">
        <signature>
          <arg nr="1">
            <long/>
          </arg>
          <arg nr="2">
            <int/>
          </arg>
        </signature>
      </method>
      <!-- ~~~~~~~~~~~~~~~~~~~~~~~~~~~~~~~~~~~~~~~~~~~~~~~~~~~~ (inherited) wait -->
      <method from="java.lang.Object" inherited="yes" name="wait">
        <signature>
          <arg nr="1">
            <long/>
          </arg>
        </signature>
      </method>
    </methods>
  </class>
  <copyright-notice>Copyright 2012-2020, Kestrel Technology LLC, Palo Alto, CA 94304</copyright-notice>
</codehawk-java-analyzer>
